api/README.md
api/__init__.py
api/client/__init__.py
api/client/batch_client/__init__.py
api/client/cfg/__init__.py
api/client/crop_model/__init__.py
api/client/gro_client/__init__.py
api/client/lib/__init__.py
api/client/samples/__init__.py
api/client/samples/analogous_years/__init__.py
api/client/samples/analogous_years/lib/__init__.py
api/client/samples/analogous_years/lib/distance_matrix.py
api/client/samples/analogous_years/lib/distance_matrix_test.py
api/client/samples/analogous_years/lib/feature_extractions.py
api/client/samples/analogous_years/lib/feature_extractions_test.py
api/client/samples/analogous_years/lib/final_ranks_computation.py
api/client/samples/analogous_years/lib/final_ranks_computation_test.py
api/client/samples/analogous_years/lib/get_transform_data.py
api/client/samples/analogous_years/lib/get_transform_data_test.py
api/client/samples/analogous_years/lib/utils/__init__.py
api/client/samples/analogous_years/lib/utils/validation.py
api/client/samples/analogous_years/readme.md
api/client/samples/analogous_years/requirements.txt
api/client/samples/analogous_years/run_analogous_years.py
api/client/samples/crop_models/README.md
api/client/samples/crop_models/__init__.py
api/client/samples/crop_models/cash_crops.py
api/client/samples/crop_models/crop_model.py
api/client/samples/crop_models/requirements.txt
api/client/samples/crop_models/soybeans.py
api/client/samples/crop_models/sugar.py
api/client/samples/quick_start.py
api/client/samples/search.py
groclient/__init__.py
groclient/__main__.py
groclient/batch_client_test.py
groclient/cfg.py
groclient/cli.py
groclient/client.py
groclient/client_test.py
groclient/constants.py
groclient/crop_model.py
groclient/experimental.py
groclient/experimental_test.py
groclient/lib.py
groclient/lib_test.py
groclient/mock_data.py
groclient/utils.py
groclient/utils_test.py
groclient-1.369.1.dist-info/entry_points.txt
groclient-1.369.1.dist-info/LICENSE
groclient-1.369.1.dist-info/WHEEL
groclient-1.369.1.dist-info/METADATA
groclient-1.369.1.dist-info/RECORD
